{
  "title": "Экскурсии для детей по магазинам ВкусВилл 6+ Откуда берётся еда на полках магазинов? Юным исследователям предстоит выяснить это на интерактивных...",
  "dates": "до 4 апреля пн–пт весь день 5000 рублей за группу от 5 до 15 человек Записать группу ",
  "price": "348 Р",
  "link": "https://kudago.com/msk/event/detyam-ekskursii-dlya-detej-po-magazinam-vkusvill/",
  "source_url": "https://kudago.com/msk/excursions/",
  "page_type": "event",
  "city": "moscow",
  "site": "moscow_kudago",
  "parsed_timestamp": "2026-03-18 19:49:17"
}