{
  "title": "Концерт «Old Hollywood и Золотой век джаза» Георгия Тадоровского и Tadorovsky Band 12+ Гости вечера перенесутся во времена Великого Гэтсби, романтичную эпоху великосветских джазовых вечеринок и...",
  "dates": "23 марта 19:30",
  "place": "Англиканская церковь Cвятого Андрея от",
  "price": "2000 руб",
  "description": "827 лей Купить билеты ",
  "link": "https://kudago.com/msk/event/kontsert-georgij-tadorovskij-itadorovsky-band/",
  "source_url": "https://kudago.com/msk/concerts/",
  "page_type": "event",
  "city": "moscow",
  "site": "moscow_kudago",
  "parsed_timestamp": "2026-03-18 19:49:04"
}