[
  {
    "title": "Беременность и роды",
    "link": "https://gu.spb.ru/knowledge-base/o-beremennost-i-rody/",
    "content": "Беременность и родыБеременные женщины имеют право на декретный отпуск, а также связанные с этим выплаты. Декретный отпуск включает в себя два вида отпуска, которые следуют друг за другом.Отпуск по беременности и родам— обычно он длится 140 дней: 70 дней до родов и 70 дней после. В случае многоплодной беременности продолжительность отпуска увеличивается до 194 дней, а при родах с осложнениями — до 156.Отпуск по уходу за ребёнком— предоставляется до исполнения ребёнку 3 лет без прерывания трудового стажа и стажа работы по специальности.Отпуск по уходу за ребенком до 3 лет положен его матери, отцу, бабушке или другому родственнику, занятому уходом за ребенком. Во время отпуска выплачивается пособие по уходу за ребенком до 1,5 лет. Отпуск по беременности и родам— обычно он длится 140 дней: 70 дней до родов и 70 дней после. В случае многоплодной беременности продолжительность отпуска увеличивается до 194 дней, а при родах с осложнениями — до 156. Отпуск по уходу за ребёнком— предоставляется до исполнения ребёнку 3 лет без прерывания трудового стажа и стажа работы по специальности.Отпуск по уходу за ребенком до 3 лет положен его матери, отцу, бабушке или другому родственнику, занятому уходом за ребенком. Во время отпуска выплачивается пособие по уходу за ребенком до 1,5 лет. Уйти в декретный отпуск могут все работающие женщины вне зависимости от стажа, а также те, кто состоит на учёте в Службе занятости, студентки очной формы обучения и находящиеся на военной службе или в женской части гражданского персонала военных учреждений.Шаг1Начало декретного отпуска определяется датой оформления больничного листа. На сроке 30 недель (или 28, если беременность многоплодная) женщина получает у врача женской консультации листок нетрудоспособности и заверяет его у своего руководителя.Шаг2Далее необходимо написать заявление на предоставление отпуска по беременности и родам своему работодателю. В документе обязательно указывается причина будущего отсутствия на работе, сроки, вычисленные по больничному листу, и пункт о начислении соответствующих пособий, иначе их оформлением придётся заниматься отдельно.Шаг3Отдел кадров на основании заявления и больничного листа оформляет приказ о предоставлении отпуска. Будущая мама полностью свободна от трудовых забот с даты, указанной в приказе.Шаг4После окончания отпуска по беременности и родам нужно на имя работодателя написать заявление на предоставление отпуска по уходу за ребёнком, приложив к нему свидетельство о рождении.Отпуск по уходу за ребёнком может быть использован полностью или по частям также папой, бабушкой, дедушкой, другим родственником или опекуном, фактически осуществляющим уход за ребёнком.Находясь в отпуске по уходу за ребёнком, вы можете работать на условиях неполного рабочего времени или на дому. Необходимо будет написать соответствующее заявление. Право на получение пособия по уходу за ребёнком при этом сохраняется. Отпуск по уходу за ребёнком может быть использован полностью или по частям также папой, бабушкой, дедушкой, другим родственником или опекуном, фактически осуществляющим уход за ребёнком. Подать заявление на получение пособия можно 3 способами в зависимости от категории, к которой относится беременная женщина:работающие — на работе, представляется только листок нетрудоспособности;уволенные в связи с ликвидацией организации — в клиентской службе Социального фонда России (СФР) или в МФЦ (чтобы выбрать удобный способ подачи заявления — перейдитепо ссылке)."
  },
  {
    "title": "Материнский капитал",
    "link": "https://gu.spb.ru/knowledge-base/o-materinskiy-kapital/",
    "content": "Материнский капиталМатеринский капитал представляет собой сертификат на определённую сумму, размер которой ежегодно индексируется. Материнский (семейный) капитал — это мера государственной поддержки семей, в которых:с 2007 года родился или был усыновлён второй ребёнок (а также третий, четвертый и любой следующий, если до этого право на материнский капитал не оформлялось);начиная с 1 января 2020 года появилсяпервыйребёнок. 630 380,77 руб.— на первого ребёнка (дата рождения с 1 января 2020 года)630 380,77 руб.— на второго ребёнка (дата рождения до 1 января 2020 года)202 643,96 руб.— на второго ребёнка (дата рождения с 1 января 2020 года)Общая сумма составляет833 024,74 руб.833 024,74 руб.— на третьего (последующего) ребёнка (дата рождения с 1 января 2020 года), если до этого право на маткапитал не оформлялось 630 380,77 руб.— на первого ребёнка (дата рождения с 1 января 2020 года) 630 380,77 руб.— на второго ребёнка (дата рождения до 1 января 2020 года) 202 643,96 руб.— на второго ребёнка (дата рождения с 1 января 2020 года)Общая сумма составляет833 024,74 руб. 833 024,74 руб.— на третьего (последующего) ребёнка (дата рождения с 1 января 2020 года), если до этого право на маткапитал не оформлялось Для получения сертификата мать и ребёнок, с рождением которого возникает право на получение сертификата, должны быть гражданами Российской Федерации.На получение сертификата имеет право:Шаг1Мама, у которой родился (или усыновлён) второй, третий или последующий ребёнок с 1 января 2007 года.Шаг2Мама, у которой родился (или усыновлён) первый ребёнок начиная с 1 января 2020 года.Шаг3Папа, имеющий российское гражданство, если онединственныйусыновитель второго, третьего или последующего ребёнка (решение суда об усыновлении вступило в законную силу начиная с 1 января 2007 года).Шаг4Папанезависимо от наличия у него гражданства РФв случае, если у матери прекращается право на получение материнского капитала.Шаг5Папа, имеющий российское гражданство, если он является единственным усыновителем первого ребёнка (решение суда об усыновлении которого вступило в законную силу начиная с 1 января 2020 года).Шаг6Несовершеннолетний ребёнок (либо дети в равных долях), а также совершеннолетний ребёнок, получающий образование по очной программе до окончания обучения, но не дольше, чем до достижения им 23‑летнего возраста, если у\r\n\t\t\t\t\t\t\tродителей (усыновителей) прекратилось право на получение материнского капитала. С 15 апреля 2020 года сертификат на материнский капитал оформляется автоматически, без подачи заявления. Информация о получении семьёй материнского капитала направляется в личный кабинет владельца сертификатана сайте Социального фонда России(СФР) илина федеральном портале gosuslugi.ru.Семья может распоряжаться материнским капиталом, получив сертификат в электронной форме.Для семей с приёмными детьми сохраняется прежний порядок оформления сертификата, поскольку сведения об усыновлении могут представить только сами приёмные родители.Подать заявление на получение сертификата можно в отделениях СФР, в МФЦ или\r\n\t\t\t\t\tэлектронным способом. Чтобы выбрать удобный способ подачи — перейдитепо ссылке. Заявление на распоряжение средствами материнского капитала подаётся после его оформления. При этом потратить средства можно только на определённые цели, воспользовавшись сразу всей суммой либо только её частью. Возможны следующие варианты использования материнского капитала.Накопительная пенсия мамыСредства материнского капитала могут быть включены в состав пенсионных накоплений и переданы в доверительное управление управляющей компании или в негосударственный пенсионный фонд. Подать заявление можночерез 3 годапосле рождения (усыновления) ребёнка.Образование детейНаправить материнский капитал на образование любого из детей можно, когда ребёнку, рождение которого даёт право на сертификат,исполнится 3 года.Исключение составляет дошкольное образование — по\r\n\t\t\t\t\tэтому направлению материнским капиталом можно распорядиться сразу после рождения (усыновления) ребёнка, который даёт право на сертификат.Улучшение жилищных условийНаправить материнский капитал на улучшение жилищных условий можно, когда ребёнку, в связи с рождением (усыновлением) которого возникло право на получение сертификата,исполнится три года.Исключение —\r\n\t\t\t\t\tуплата первоначального взноса или погашение долга по жилищному кредиту либо займу. В этом случае воспользоваться материнским капиталом можно сразу.Ежемесячная выплата из средств материнского капиталаС 2023 года выплата назначается на любого по счёту ребёнка до 3 лет. Средний доход на каждого члена семьи в месяц не должен превышать двух региональных прожиточных минимумов на душу населения. Учитываются доходы за 12 месяцев, предшествующих одному месяцу до месяца обращения.Пособие выплачивается в размере одного регионального прожиточного минимума для детей. Подавать заявление можно в любое время в течение трёх лет со дня рождения ребёнка.Социальная адаптация и интеграция в общество детей‑инвалидовСредствами материнского капитала можно компенсировать затраты на покупку товаров и услуг для социальной адаптации и интеграции в общество детей‑инвалидовпо утверждённому перечню. Подать заявление можнов любое времяпосле рождения (усыновления) ребёнка.Единовременная выплатаЕсли после распоряжения средствами маткапитала остаток на сертификате менее10 000 руб., можно получить единовременную выплату. Она предоставляется в размере фактического остатка средств. Подать заявление можно в любое время после возникновения права на получение единовременной выплаты.Чтобы воспользоваться средствами, нужноподать заявление на распоряжение средствами материнского капитала. На нашем портале доступен сервис:Проверка статуса решения по заявлению о выдаче сертификата на материнский капитал или распоряжению средствами"
  },
  {
    "title": "Перевод ребёнка в другую школу",
    "link": "https://gu.spb.ru/knowledge-base/o-perevod-rebenka-v-druguyu-shkolu/",
    "content": "Перевод ребёнка в другую школуПорой может возникнуть ситуация, когда ребёнку нужно поменять школу. Например, если семья переезжает в другой район. Здесь мы собрали полезную информацию для родителей, которые планируют перевести ребёнка в другое образовательное учреждение. Перевести ребёнка в другую школу можно в любое время года. Главное — чтобы в ней были свободные места.Узнать о том, есть ли они, можно заранее — такая информация размещается на сайте образовательного учреждения. Если же данных нет, можно позвонить в канцелярию школы или посетить её лично.При отсутствии вакантных мест в желаемой школе обратитесьв отдел образования местной администрации.Подать заявление о переводе может один из родителей или законных представителей ребёнка (опекун, приёмный родитель), а также доверенное лицо на основании доверенности. Перевести ребёнка в другую школу можно в любое время года. Главное — чтобы в ней были свободные места.Узнать о том, есть ли они, можно заранее — такая информация размещается на сайте образовательного учреждения. Если же данных нет, можно позвонить в канцелярию школы или посетить её лично.При отсутствии вакантных мест в желаемой школе обратитесьв отдел образования местной администрации. Подать заявление о переводе может один из родителей или законных представителей ребёнка (опекун, приёмный родитель), а также доверенное лицо на основании доверенности. Прежде чем подавать заявление в 5-11 классы в школы с углубленным изучением отдельных предметов, удостоверьтесь, что ребёнка готовы принять в новое образовательное учреждение. Чтобы проверить уровень знаний, такие школы устраивают тестирование по основным предметам.Подать заявление о приёме в школу можно онлайн, в любом удобном многофункциональном центре (МФЦ) или обратившись лично в выбранную школу.Подать заявление онлайн Обязательно понадобятся:паспорт родителя (законного представителя), который подаёт заявление;свидетельство о рождении ребёнка (или паспорт, если ему исполнилось 14 лет);аттестат об основном общем образовании (при переводе в десятый-одиннадцатый/двенадцатый классы).Полный список документов —по этой ссылке.Если вы подаёте заявление на льготных основаниях, право ребёнка на внеочередной, первоочередной или преимущественный приём потребуется подтвердить (например, свидетельством о рождении брата или сестры, которые учатся в выбранной школе). По регламентуприглашение от школы придет в течение 15 рабочих дней со дня подачи заявления. С приглашением обратитесь в школу, которую ребёнок покидает, и напишите заявление об отчислении. Школа его зарегистрирует и издаст распорядительный акт об отчислении.На руки вам должны выдать:личное дело ребёнка;табель с текущими оценками (или справку об успеваемости);медицинскую карту (в том числе карту профилактических прививок).Эти сведения, а также оригиналы документов, копии которых вы представляли при подаче заявления, нужно отнести в новую школу в указанное в приглашении время.Зачислят ребёнка в течение 5 рабочих дней после их приёма. С приглашением обратитесь в школу, которую ребёнок покидает, и напишите заявление об отчислении. Школа его зарегистрирует и издаст распорядительный акт об отчислении.На руки вам должны выдать:личное дело ребёнка;табель с текущими оценками (или справку об успеваемости);медицинскую карту (в том числе карту профилактических прививок). Если школа прекращает работать или лишается лицензии, онадолжнаписьменно предупредить родителей в течение 5 рабочих дней с момента издания соответствующего акта. Уведомление о прекращении деятельности также размещается на официальном сайте школы.В уведомлении указывается школа, готовая принять учеников, а также срок, в течение которого родители должны принести письменное согласие на перевод.Получив согласие, принимающая школа издаёт распорядительный акт о зачислении с указанием класса, формы обучения и школы, в которой ребёнок обучался до перевода."
  },
  {
    "title": "Путёвки в детские лагеря",
    "link": "https://gu.spb.ru/knowledge-base/o-oplata-detskikh-ozdorovitelnykh-lagerey/",
    "content": "Путёвки в детские лагеряДети, живущие в Санкт-Петербурге, могут на льготных условиях получать путёвки в лагеря дневного пребывания на базе школ, а также в детские оздоровительные или санаторно-оздоровительные лагеря.Список дневных лагерей и даты смен можно уточнить в администрации района по месту жительства ребёнка, а информацию о загородных оздоровительных лагерях — получить вЦентре оздоровления и отдыха «Молодежный». Путёвки в детские оздоровительные или санаторно-оздоровительные лагеря для детей, проживающих в Санкт-Петербурге, полностью или частично оплачиваются из городского бюджета:Детям работающих родителейгород оплачивает 60% от стоимости путёвки. Ребёнку должно быть от 6 лет и 6 месяцев до 15 лет.Детям из спортивных или творческих коллективовгород оплачивает 60% от стоимости путёвки. Ребёнку должно быть от 6 лет 6 месяцев до 17 лет.Детям-льготникам*, в том числе детям-инвалидам, детям-сиротам, детям из неполных семей идругим категориям, путёвку полностью оплачивает город. Путёвка будет предоставлена в лагерь, с которым заключит контракт администрация района Санкт-Петербурга.*Для детей-инвалидов возможен отдых в российском санатории. В санаторно-курортной организации должна быть предусмотрена материально-техническая база и иные условия для круглосуточного пребывания детей-инвалидов, в том числе беспрепятственный доступ к объектам и предоставляемым в них услугам.Посмотреть полный перечень обязательных документов для каждой категории заявителя можно поссылке.Как отправить ребёнка в лагерь?Шаг1Подготовить документы и подать заявление онлайн, в МФЦ или в Санкт Петербургское государственное бюджетное учреждение «Центр оздоровления и отдыха «Молодёжный» (СПб ГБУ ЦОО «Молодёжный») (выбрать удобный способ подачи —для детей работающих родителей;для детей-льготников).Шаг2Получить сертификат на частичную или полную оплату стоимости путёвки.В электронном виде сертификат не предоставляется, так как подлежит строгой финансовой отчётности.Шаг3Выбрать лагерьиз перечня.Шаг4Заключить договор с лагерем.Шаг5Для всех, кроме льготников: частично оплатить стоимость путёвки с учётом сертификата (в случаях, когда город берёт на себя 100% стоимости, оплата не нужна вовсе).Шаг6Отправить ребёнка отдыхать.Родитель должен представить сертификат в лагерь в течение 30 календарных дней с момента получения, но не позднее дня начала смены.Решение о предоставлении путёвок в загородные лагеря с полной оплатой стоимости принимают районные комиссии по организации отдыха детей и молодёжи и их оздоровления. Подготовить документы и подать заявление онлайн, в МФЦ или в Санкт Петербургское государственное бюджетное учреждение «Центр оздоровления и отдыха «Молодёжный» (СПб ГБУ ЦОО «Молодёжный») (выбрать удобный способ подачи —для детей работающих родителей;для детей-льготников). Получить сертификат на частичную или полную оплату стоимости путёвки.В электронном виде сертификат не предоставляется, так как подлежит строгой финансовой отчётности. Выбрать лагерьиз перечня. Заключить договор с лагерем. Для всех, кроме льготников: частично оплатить стоимость путёвки с учётом сертификата (в случаях, когда город берёт на себя 100% стоимости, оплата не нужна вовсе). Отправить ребёнка отдыхать. Дети от 6 лет 6 месяцев до 17 лет, живущие в Санкт-Петербурге, могут отдохнуть в одном из лагерей дневного пребывания, которые создаются в школах на время летних каникул. Заявление можно подать в любую школу города – и получить место с полной или частичной оплатой за счёт бюджета Санкт-Петербурга:детям работающих родителейгород оплачивает 60% от стоимости путёвки;детям-льготникампутёвку полностью оплачивает город.Посмотреть полный перечень обязательных документов для каждой категории заявителя можно поссылке.Предварительное решение о зачислении в лагерь принимается в течение 7 рабочих дней после подачи заявления. Работающие родители также получат квитанцию на оплату части стоимости. Окончательный список детей формируется не позднее 5 рабочих дней до начала смены.Оригиналы документов, приложенные при подаче электронного заявления, затем предоставляются в школу лично. Оригиналы документов, приложенные при подаче электронного заявления, затем предоставляются в школу лично."
  },
  {
    "title": "Внеурочная деятельность и группы продлённого дня",
    "link": "https://gu.spb.ru/knowledge-base/o-vneurochnaya-deyatelnost-i-gruppy-prodlennogo-dnya/",
    "content": "Внеурочная деятельность и группы продлённого дняКроме уроков, по учебному плану в школах есть внеурочная деятельность и группы продлённого дня. Нет. В школах Санкт‑Петербурга родителям не нужно дополнительно оплачивать присмотр за детьми в группах продлённого дня. Семьи, у которых нет льгот, оплачивают только питание ребёнка. Внеурочная деятельность является частью образовательной программы, но родители могут определять количество занятий, кружков и секций. Внеурочная деятельность может включать в себя классные часы, экскурсии, занятия по интересам, круглые столы, конференции, школьные научные общества, олимпиады, соревнования, поисковые и научные исследования, проектную\r\n\t\t\t\t\tдеятельность и т.д.Для детей, посещающих музыкальные, спортивные, художественные школы, кружки в домах детского творчества, внеурочная деятельность может быть существенно сокращена. Для детей, посещающих музыкальные, спортивные, художественные школы, кружки в домах детского творчества, внеурочная деятельность может быть существенно сокращена."
  },
  {
    "title": "Социальная поддержка родителей школьников",
    "link": "https://gu.spb.ru/knowledge-base/o-sotsialnaya-podderzhka-roditeley-shkolnikov/",
    "content": "Уважаемые заявители! В связи с проведением плановых технических работ в период с 15:00 17.03.2026 и до окончания проведения работ подача заявлений может быть временно недоступна. Приносим извинения за доставленные неудобства. Социальная поддержка родителей школьниковНекоторым школьникам и их семьям полагаются меры социальной поддержки. Здесь вы узнаете, на какие льготы можете рассчитывать и как их оформить. Компенсация питания в школах зависит от класса, в котором обучается школьник, и от права его семьи на льготы.С 2020 года бесплатное питание полагается всем ученикам 1-4 классов.Если у вас есть льготы и вы хотите подать заявление на обеспечение ребёнка питанием в школе, обратитесь в МФЦ или\r\n                    в образовательное учреждение (выбрать удобный способ обращения можноздесь).Изучить подробную информацию о возможных видах компенсации питания для школьников и учащихся профессиональных образовательных учреждений вы можетепо ссылке. Изучить подробную информацию о возможных видах компенсации питания для школьников и учащихся профессиональных образовательных учреждений вы можетепо ссылке. Пособие назначается малообеспеченным семьям на детей в возрасте от 7 до 16 лет (либо по месяц окончания школы, но не старше 18 лет). Подтверждать право на выплату нужно ежегодно.В 2025 году размер пособия - 1 289 руб.Неполной семье и семье военнослужащего полагается 1 864 руб.Подать заявление можно онлайн на портале, в МФЦ или\r\n                    в администрации района Санкт‑Петербурга (чтобы выбрать удобный способ подачи заявления — перейдитепо ссылке). Если вашему ребёнку не положены бесплатные льготные завтраки и обеды, вы можете оплатить их самостоятельно.Для оплаты школьного питания вы можете перевести средства на лицевой счёт ребёнка двумя способами:через личный кабинет напортале;через раздел«Оплата».Также доступны другие способы оплаты:портал«Петербургское образование»;сайт«Моя школа»;сервисы банков-партнёров.Инструкция по оплате школьного питания"
  }
]