[
  {
    "title": "Единая карта петербуржца «Серебряный возраст»",
    "link": "https://gu.spb.ru/knowledge-base/serebryanyy-vozrast/",
    "content": "Единая карта петербуржца «Серебряный возраст»ЕКП «Серебряный возраст» — это Единая карта петербуржца (ЕКП) в особом дизайне. Карту могут оформить женщины и мужчины, достигшие возраста 55 и 60 лет соответственно. ЕКП «Серебряный возраст» на базе Единой карты петербуржца (ЕКП) даёт возможность использовать её как банковскую карту, проездной в транспорте, получать льготы и скидки, предназначенные для людей пенсионного и\r\n                    предпенсионного возраста. Чтобы оформить ЕКП «Серебряный возраст», необходимо обратиться в отделение одного из пяти банков-партнёров ЕКП:Сбер БанкВТББанк «Санкт-Петербург»ГазпромбанкПСБДля оформления понадобятся паспорт и СНИЛС.Срок изготовления карты составляет от 8 до 14 дней.С полной информацией о ЕКП «Серебряный возраст» можно ознакомиться поссылке. Если у Вас уже есть ЕКП, переоформлять её на ЕКП «Серебряный возраст» необязательно. Держатели ЕКП, попадающие под действие программы, автоматически будут подключены к ней.Если Вы хотите, чтобы карта ЕКП была в дизайне «Серебряный возраст», Вам необходимо написать заявление на переоформление карты. Сделать это можно в том банке, где была выпущена Ваша ЕКП. Срок переоформления карты – до 14\r\n                    дней.Если вы хотите выпустить ЕКП «Серебряный возраст» в другом банке, вам нужно сначала закрыть карту ЕКП в том банке, где Вы ее оформляли, а потом написать заявление на выпуск ЕКП «Серебряный возраст» в одном из\r\n                    банков-партнеров ЕКП. С 1 марта 2025 года для держателей карты будет доступен электронный сертификат на покупку билетов в музеи. Средствами сертификата можно будет воспользоваться для покупки входных билетов в федеральные (Эрмитаж, Русский\r\n                    музей и др.) и городские музеи.Номинал сертификата – 1 500 руб. в год.Со списком музеев, посещение которых доступно по электронному сертификату, можно ознакомитьсяна портале ЕКП. Чтобы получить электронный сертификат, нужно:Иметь ЕКП или ЕКП «Серебряный возраст».Достигнуть возраста 55 лет (для женщин), 60 лет (для мужчин).Иметь регистрацию по месту жительства в Санкт-Петербурге.Быть гражданином Российской Федерации.Более подробную информацию можно узнатьна странице услуги. Сертификат действует 12 месяцев.Мера поддержки предоставляется ежегодно до 1 января 2028 года. Вы можете выбрать любой удобный способ:подать заявление на получение электронного сертификатана странице услуги;подать заявление через МФЦ.С подробной инструкцией по заполнению электронного заявления можно ознакомиться поссылке. Оформление электронного сертификата займёт от 5 до 10 рабочих дней. Билеты по электронному сертификату можно приобрести в кассах музея через специальный терминал. После прикладывания карты к терминалу необходимо будет ввести пин-код карты ЕКП.Билеты приобретаются по тарифам музеев с учётом льготных категорий. Подробная информация о ЕКП «Серебряный возраст», электронном сертификате –на портале ЕКП.С ответами на часто задаваемые вопросы о ЕКП «Серебряный возраст» можно ознакомитьсяздесь.Единый телефон для справок:8 (812) 417-53-35. Проверить остаток средств на сертификате можнов личном кабинете на портале.1Зайдите на портал поссылкес помощью своего логина и пароля ЕСИА2Ознакомьтесь с информацией и нажмите «Запросить выписку»3Выписка поступит в ваш личный кабинет на региональном портале госуслуг в течение суток"
  },
  {
    "title": "Подарочный набор для новорождённых петербуржцев",
    "link": "https://gu.spb.ru/knowledge-base/podarochnyy-nabor-dlya-novorozhdyennykh-peterburzhtsev/",
    "content": "Подарочный набор для новорождённых петербуржцевС 1 августа 2024 года мамы и папы смогут получить «приданое» для новорождённого – подарочный набор с детскими принадлежностями. Это дополнительная мера поддержки к уже имеющимся федеральным и региональным выплатам на детей. Подарок сэкономит финансы и позволит провести больше времени с малышом. С 1 августа 2024 года вступили в силу изменения вСоциальный кодекс Санкт-Петербурга, согласно которым\r\n\t\t\t\t\tродители могут бесплатно получить подарочный комплект детских принадлежностей для своего новорождённого малыша при государственной регистрации рождения в органе ЗАГС Санкт-Петербурга.Перечень принадлежностей определёнраспоряжением Комитета по делам записи актов гражданского состояния от 27 мая 2024 года № 7с\r\n\t\t\t\t\tучётом мнений представителей некоммерческих организаций, медицинских работников и родителей. В состав набора входит 12 наименований:видеоняня;увлажнитель воздуха;подогреватель детского питания;ночник с мягким корпусом;стерилизатор для бутылочек и сосок;интерактивная музыкальная игрушка;погремушка развивающая;набор детских игрушек;игрушка для купания;полотенце;коврик развивающий;брошюра. Нет, подарки являются универсальными и предназначены для детей любого пола. Подарочный набор могут получить семьи, в которых хотя бы один родитель является гражданином России и имеет место постоянного жительства в Санкт-Петербурге, а ребёнок рождён начиная с 1 августа 2024 года. Нет, хотя бы у одного из родителей должна быть постоянная регистрация в Санкт-Петербурге. Чтобы получить подарочный набор для новорождённого, необходимо подать соответствующее заявление. Заявителем должен быть один из родителей новорождённого, являющийся гражданином Российской Федерации, имеющий постоянное\r\n\t\t\t\t\tместо жительства в Санкт-Петербурге. Заявление на получение подарочного набора также имеет право подать представитель, действующий на основании доверенности, в том числе сотрудники городских медицинских организаций, в\r\n\t\t\t\t\tкоторых проходили роды, осуществляющих медицинскую деятельность по профилю «акушерство и гинекология» и оказывающих медицинские услуги по родовспоможению.К заявлению нужно приложить:документ, удостоверяющий личность заявителя;копию справки о регистрации по месту жительства заявителя (форма 9), копию свидетельства о регистрации по месту жительства заявителя (форма 8) или копию решения суда об установлении места жительства заявителя в\r\n\t\t\t\t\t\tСанкт-Петербурге (если сведения о месте жительства отсутствуют в документе, удостоверяющем личность);документ, удостоверяющий личность представителя, и документ, подтверждающий полномочия представителя (при подаче заявления представителем). Заявление на получение подарочного набора необходимо подать в орган ЗАГС Санкт-Петербурга. Сделать это можно непосредственно в органе ЗАГС Санкт-Петербурга при государственной регистрации рождения ребёнка, а также через МФЦ или медицинскую организацию, в\r\n\t\t\t\t\tкоторой происходили роды, до момента выписки матери ребёнка. В случае, если рождение было зарегистрировано, но подарок не был выдан, соответствующее заявление подаётся в тот орган ЗАГС Санкт-Петербурга, в котором зарегистрировано\r\n\t\t\t\t\tрождение. Решение о выдаче подарочного комплекта принимается в течение одного рабочего дня с момента регистрации в органе ЗАГС Санкт-Петербурга соответствующего заявления.Если заявление подано через МФЦ или медицинскую организацию, то срок увеличивается на время, необходимое для передачи документов в орган ЗАГС Санкт-Петербурга. Нет, денежная компенсация взамен подарочного комплекта для новорождённого не предусмотрена. Получить подарочный набор можно:в медицинской организации, в которой происходили роды (при подаче заявления на получение подарочного набора через медицинскую организацию);в МФЦ (при подаче соответствующего заявления через МФЦ);в органе ЗАГС Санкт-Петербурга.Если в получении подарка органом ЗАГС Санкт-Петербурга было отказано, заявителю (представителю) выдаётся письменное уведомление об отказе. По месту государственной регистрации рождения ребёнка. Перечень медицинских организаций, которые оказывают содействие родителям в государственной регистрации рождения новорождённого и в предоставлении подарочного набора, постоянно изменяется, в связи с чем актуальную\r\n\t\t\t\t\tинформацию по данному вопросу необходимо уточнять непосредственно в медицинской организации, в которой будут происходить роды. Это возможно в случае, если роддом оказывает содействие родителям в государственной регистрации рождения новорождённого и в предоставлении подарочного набора на основании соглашения между роддомом иКомитетом по делам записи актов гражданского состояния. Да, если хотя бы один родитель имеет гражданство России и место постоянного жительства в Санкт-Петербурге, а ребёнок рождён не ранее 1 августа 2024 года и его рождение зарегистрировано в органе ЗАГС Санкт-Петербурга. Нет, подарочный набор выдаётся детям, родившимся начиная с 1 августа 2024 года (согласнопостановлению Правительства Санкт-Петербурга от 23 мая 2024 года № 365). В течение шести месяцев с момента рождения ребёнка. При рождении двух и более детей подарочный комплект вручается на каждого малыша. Да. В случае, если при государственной регистрации рождения подарочный набор не вручался, то родитель (один из родителей) может получить подарочный комплект при соблюдении требований законодательства. Да, такое возможно. Комитет по делам записи актов гражданского состояния проводит анализ общественного мнения по составу подарка новорождённого, на основании которого принимается решение о необходимости внесения\r\n\t\t\t\t\tизменений/отсутствии необходимости внесении изменений в состав подарочного комплекта. Подарочный набор – дополнительная мера социальной поддержки, которая не станет заменой уже существующим выплатам.Каждой семье новорождённого в городе предусмотрены единовременная компенсационная выплата на покупку детских вещей, единовременное пособие при рождении ребёнка, ежемесячное пособие по уходу за ребёнком до 1,5 лет.Дополнительную выплату могут получить родители-студенты очных отделений, а также женщины в возрасте от 19 до 24 лет включительно, родившие первого ребёнка в период с 1 января 2020 года.Пособия также предусмотрены, если, например, малыш является инвалидом, ВИЧ-инфицированным, растёт в многодетной, неполной семье.Подробнее о выплатах при рождении ребёнка, первых документах малыша можно узнать поссылке."
  },
  {
    "title": "Как настроить уведомления в личном кабинете на портале",
    "link": "https://gu.spb.ru/knowledge-base/kak-nastroit-uvedomleniya-v-lichnom-kabinete-na-portale/",
    "content": "Как настроить уведомления в личном кабинете на порталеС помощью портала госуслуг Санкт-Петербурга можно получить более 200 государственных услуг, подав заявление онлайн. У каждой услуги есть свой порядок рассмотрения и срок оказания. После подачи заявления вы можете отслеживать ход его рассмотрения в личном кабинете на портале. Здесь вы узнаете, как настроить получение уведомлений. Чтобы не пропустить обновления статуса заявления, настройте получение уведомлений в настройках личного кабинета.E-mail— в случае изменения статуса заявления на электронную почту, указанную в профиле, придёт письмо с соответствующей информацией и ссылкой на заявление в личном кабинете на портале.ВКонтакте— уведомление с новым статусом заявления придёт в ваш аккаунт социальной сети ВКонтактеот официального сообщества «ГосуслугиСанкт-Петербурга».Подписаться на группу ВКонтакте:Push-уведомленияс новым статусом заявления отобразится на экране вашего смартфона, если у вас установленомобильное приложение «Госуслуги Санкт-Петербурга».SMS— когда статус заявления изменится, на номер телефона, указанный в вашем профиле, придет SMS с текстом, что статус заявления изменился. Важно: сообщение ограничено по количеству символов, поэтому,\r\n\t\t\t\t\tиспользуя данный вид уведомления, вы не получаете полную информацию. Статус заявления и комментарий к нему от представителя ведомства вы сможете увидеть, заглянув в личный кабинет на портале gu.spb.ru (в разделе\r\n\t\t\t\t\t«Заявления») илив мобильное приложение.Скачать мобильное приложение: Шаг1Авторизуйтесь на портале госуслуг Санкт-Петербурга с помощью логина и пароля вашей учётной записи ЕСИА.Шаг2Войдите в профиль вашей учётной записи.Шаг3В меню профиля войдите в пункт «Настройки».Шаг4Откроются настройки уведомлений. Выберите пункт «Изменение статуса» заявлений, поданных через портал» и поставьте галочки напротив тех видов уведомлений, которые вам подходят. Авторизуйтесь на портале госуслуг Санкт-Петербурга с помощью логина и пароля вашей учётной записи ЕСИА. Войдите в профиль вашей учётной записи. В меню профиля войдите в пункт «Настройки». Откроются настройки уведомлений. Выберите пункт «Изменение статуса» заявлений, поданных через портал» и поставьте галочки напротив тех видов уведомлений, которые вам подходят."
  },
  {
    "title": "Согласование уличных выступлений в Санкт-Петербурге",
    "link": "https://gu.spb.ru/knowledge-base/soglasovanie-ulichnykh-vystupleniy-v-sankt-peterburge/",
    "content": "Согласование уличных выступлений в Санкт-ПетербургеС 1 мая 2023 года введены новые правила организации уличных выступлений. Теперь, прежде чем поделиться с горожанами исполнительским искусством, необходимо заранее согласовать с органами власти место и время представления, а также список музыкальных инструментов, если такие будут использоваться. Если выступление планируется на Дворцовой площади, тогда заявку на согласование нужно подать в Комитет по культуре Санкт-Петербурга, если в других городских локациях — в соответствующую районную администрацию. Правила уличных выступлений распространяются на музыкантов, танцоров, исполнителей литературных произведений, организаторов выставок и любых других мероприятий, если они проводятся в общественных местах.\r\n\t\t\t\t\tИсключение — выступления, которые проводятся в рамках демонстрации или митинга, при праздновании свадьбы, дня рождения или во время похорон, религиозных церемоний, спортивных и физкультурных мероприятий, а\r\n\t\t\t\t\tтакже праздников и событий, включённых в городской календарь. При выборе площадки для выступления нужно учитывать категорию площадки:«без усилителя» — для проведения «тихих» выступлений;«до 250 Вт» — для проведения выступлений с использованием звукоусиливающей аппаратуры мощностью до 250 Вт и игры на ударных музыкальных инструментах на Дворцовой площади;«до 500 Вт» — для проведения выступлений с использованием звукоусиливающей аппаратуры мощностью до 500 Вт и игры на ударных музыкальных инструментах;«более 500 Вт» — для проведения выступлений с использованием звукоусиливающей аппаратуры мощностью более 500 Вт и игры на ударных музыкальных инструментах. Если на выступлении будет использоваться аппаратура со звукоусилением, то подать заявку организатор выступления или его представитель должен в периодот 10 до 20 рабочих днейдо планируемой даты\r\n\t\t\t\t\tвыступления (то есть за 21 день подавать заявку — ещё слишком рано, за 9 дней — уже поздно). Для «тихих» выступлений (без звукоусиливающего оборудования и ударных инструментов) период подачи\r\n\t\t\t\t\tсоставляетне менее 3 и не более 20 рабочих днейдо концерта. Один организатор выступления (не важно, выступает ли он сам или только организует) может подать не более 3-х заявок на выступление в разных местах за один месяц. В одной заявке можно выбрать как одну, так и несколько дат для выступлений. Однако они должны укладываться в период 30 календарных дней, для «тихих» выступлений — 14 дней, для уличных выставок — 6\r\n\t\t\t\t\tмесяцев. В одной заявке можно указать только одну площадку. Всего в течение календарного месяца можно выступатьна трёхразных площадках. Сделать это можно в электронном виде нарегиональном портале gu.spb.ru. Для этого:Шаг 11Перейдитепо ссылкеи нажмите кнопку «Получить услугу». На этом шаге будет осуществлён переход на портал\r\n\t\t\t\t\t\t\t\t\t«Культура Петербурга», где нужно выбрать интересующую площадку, а также дату и время выступления (можно выбрать один день или период из нескольких дней с указанием времени выступления для каждого\r\n\t\t\t\t\t\t\t\t\tдня).Шаг 22Ознакомьтесь с условиями выступления (то есть поставьте соответствующую галочку) и нажмите кнопку «Далее» — вы снова окажетесь на порталеgu.spb.ru.Шаг 33Авторизуйтесь на порталеgu.spb.ru, используя свою учётную запись ЕСИА (логин и пароль от госуслуг).Шаг 44Укажите в электронной заявке недостающие сведения и подтвердите их достоверность.Шаг 55Отправьте заявку и ожидайте решения о согласовании выступления. Заявки на «тихие» выступления (без звукоусиливающего оборудования и ударных инструментов) рассматриваются в течение 3-х дней, на остальные — в течение 5 дней.Информация о ходе рассмотрения заявки направляется организатору выступления уведомлениемв личный кабинет на портале gu.spb.ru. Кроме того, можно зайти на сайт администрации района или на сайт\r\n\t\t\t\t\tКомитета по культуре Санкт-Петербурга, если выступление планируется на Дворцовой площади. Можно, однако организаторы выступлений не могут подавать больше трёх заявок на выступление в одном и том же месте в течение одного календарного месяца. При этом:не более 30 дней составляет период проведения уличных выступлений с использованием звукоусиливающей аппаратуры любой мощности, а также ударных музыкальных инструментов;не более 14 дней могут длиться уличные выступления без использования звукоусиливающей аппаратуры и ударных музыкальных инструментов;не более 6 месяцев может быть отведено на проведение выставки.Выступления на Дворцовой площади могут длиться не более пяти дней. Организатор самостоятельно определяет, будут ли это пять дней подряд или отдельные дни, начиная с первого дня выступления. Соответствующая информация\r\n\t\t\t\t\tуказывается в заявке о согласовании уличных выступлений. Время выступления на Дворцовой площади не должно быть больше трех часов в день непрерывно. Нет, проведение уличных выступлений не должно иметь коммерческих целей. Нет, согласовать уличное выступление и затем выступить на улице могут только граждане старше 16 лет. Повторно согласовать выступление один организатор и (или) участник в одном и том же месте можетне ранее чем через 30 днейс последней забронированной даты выступления. Исключением из этого правила\r\n\t\t\t\t\tявляется случай, когда в согласовании было отказано в связи с тем, что иной организатор и (или) участник уличного выступления ранее согласовал выступление в этом же месте и в это же время. Нет, ограждения и рекламные щиты, дизельные генераторы, открытый огонь, пиротехника, химические вещества, гелиевые шары запрещены. Кроме того, на Дворцовой площади нельзя нарушать «стилевую и цветовую гармонию с\r\n\t\t\t\t\tархитектурным фоном» или портить мощение. Можно, но на расстоянии не ближе 10 м. Можно, но лишь в середине лета. В течение полутора месяцев действует особый график: с 15 июня до 1 августа музыканты могут выступать с 08:00 до 03:00, в остальные дни — с 10:00 до 22:00. Нет, если с момента подачи предыдущей заявки данные не изменились — снова документы прикреплять не нужно. В согласовании выступления будет отказано, если:нарушены сроки подачи заявки;один организатор подал более трёх заявок на проведение уличных выступлений в разных местах в течение календарного месяца;ещё не прошло 30 дней с того момента, как завершилось ранее согласованное уличное выступление того же организатора и (или) участника в том же месте (исключение — случаи, когда согласования не было из-за\r\n\t\t\t\t\t\tтого, что иной организатор и (или) участник ранее согласовал выступление в этом же месте и в это же время);в том месте, где заявитель хочет провести мероприятие, в указанный день (или период) проводятся ремонтно-восстановительные работы;заявка о проведении уличного выступления содержит неполную (недостоверную) информацию;документы, необходимые для согласования мероприятия, не представлены либо представлены не в полном объёме;уличное выступление имеет коммерческие цели;порядок проведения уличных выступлений в Санкт-Петербурге ранее был нарушен заявителем. Орган власти может приостановить действие согласования на выступление в следующих случаях:при повторном нарушении требований и условий проведения такого выступления;если место и время проведения ранее согласованного выступления было включено в общегородской план проведения в Санкт-Петербурге праздников и памятных дат;если возникли непредвиденные обстоятельства, которые требуют проведения специальных работ.Организатор выступления получит уведомление в срок не позднее 3-х рабочих дней с даты возникновения одного из вышеуказанных обстоятельств. Сообщение направляется организатору уличного выступления в еголичный кабинет на региональном портале. Орган власти может отозвать согласование уличного выступления в следующих случаях:если организатор выступления получил административное наказание в связи с повторным нарушением требований и условий проведения такого выступления;если место и время проведения согласованного выступления было включено в общегородской план проведения в Санкт-Петербурге праздников и памятных дат;если возникли непредвиденные обстоятельства, которые требуют проведения специальных работ.Уведомление об отзыве согласования организатор выступления получает в срок не позднее 3-х рабочих дней с даты возникновения одного из вышеуказанных обстоятельств. Сообщение направляется организатору в еголичный кабинет на региональном портале gu.spb.ru. Выступающие без предварительного согласования, а также те, кто нарушит условия согласования, получат предупреждение или должны будут уплатить штраф:от 1 500 до 5 000 руб. — для физических лиц;от 50 000 до 200 000 руб. — для юридических лиц."
  },
  {
    "title": "Ежемесячная выплата и набор социальных услуг",
    "link": "https://gu.spb.ru/knowledge-base/o-ezhemesyachnaya-vyplata-i-nabor-socialnyh-uslug/",
    "content": "Ежемесячная выплата и набор социальных услугИнвалиды любой группы и дети-инвалиды имеют право на получение ежемесячной денежной выплаты и набора социальных услуг от Социального фонда России. При установлении инвалидности ЕДВ назначается автоматически со дня признания гражданина инвалидом или ребенком-инвалидом. Подавать заявление на ее получение в этом случае не нужно. Выплата назначается на основании сведений,\r\n\t\t\t\t\tвнесенных органами медико-социальной экспертизы в Федеральный реестр инвалидов.Право на ЕДВ имеют не только люди с инвалидностью, но и ветераны, бывшие несовершеннолетние узники фашизма, люди, пострадавшие от радиации вследствие аварий и ядерных испытаний, Герои России и СССР, Герои\r\n\t\t\t\t\t\t\t\tСоцтруда, Герои Труда РФ, полные кавалеры ордена Славы и ордена Трудовой Славы.Если вы не получаете ЕДВ, но имеете на нее право, подать заявление можно онлайн, в МФЦ или в отделении СФР. Чтобы выбрать удобный способ подачи —перейдите по ссылке. Право на ЕДВ имеют не только люди с инвалидностью, но и ветераны, бывшие несовершеннолетние узники фашизма, люди, пострадавшие от радиации вследствие аварий и ядерных испытаний, Герои России и СССР, Герои\r\n\t\t\t\t\t\t\t\tСоцтруда, Герои Труда РФ, полные кавалеры ордена Славы и ордена Трудовой Славы. Сумма зависит от льготной категории, к которой относится гражданин, и складывается из размера самой выплаты и стоимости набора социальных услуг.При оформлении ЕДВ инвалидам автоматически назначается набор социальных услуг (НСУ). Размер ЕДВ можно повысить, отказавшись от НСУ. ЕДВ также будет выше при переводе на другую категорию, если у человека есть\r\n\t\t\t\t\t\t\t\tсоответствующий льготный документ.ЕДВ может предоставляться инвалидам на основании других законов, например, Федерального закона от 12.01.1995 №5-ФЗ «О ветеранах». В этом случае размер ЕДВ будет выше. Подробнее о размерах ЕДВ для различных категорий\r\n\t\t\t\t\tграждан —на сайте СФР. При оформлении ЕДВ инвалидам автоматически назначается набор социальных услуг (НСУ). Размер ЕДВ можно повысить, отказавшись от НСУ. ЕДВ также будет выше при переводе на другую категорию, если у человека есть\r\n\t\t\t\t\t\t\t\tсоответствующий льготный документ. Инвалидам, получающим ЕДВ, предоставляется набор социальных услуг (НСУ).Он включает в себя:санаторно-курортное лечение;обеспечение лекарственными препаратами;бесплатный проезд на пригородном железнодорожном транспорте, а также на междугородном транспорте к месту лечения и обратно.НСУ можно получать как в натуральной форме, так и в денежном эквиваленте. Если инвалид не пользуется социальными услугами из набора, он может отказаться от него и получать вместо этого деньги. Их включат в размер ЕДВ.С 1 февраля 2026 года размер полного набора социальных услуг  — 1 825,25 руб. в месяц.В эту сумму включается:санаторно-курортное лечение — 217,48 руб.обеспечение лекарственными препаратами — 1 405,85 руб.бесплатный проезд на пригородном железнодорожном транспорте, а также на междугородном транспорте к месту лечения и обратно — 201,92 руб.Отказаться можно как от полного набора НСУ, так и от его части. При этом размер ЕДВ увеличится на стоимость услуг, от получения которых вы отказались.ПримерИнвалиду 1 группы установлена ЕДВ в размере 5 830,70 руб. Он также получает полный набор социальных услуг в натуральном виде, поэтому из указанной суммы вычитается 1 728,46 руб. Итоговый размер выплаты составляет 4 102,24 руб.Инвалид решает отказаться от санаторно-курортного лечения и бесплатного проезда к месту лечения и заменить эти услуги на денежную компенсацию. При этом он решает сохранить право на получение лекарственных препаратов в натуральной форме. В этом случае из установленного размера ЕДВ вычтут только стоимость лекарственного обеспечения, которое и дальше будет предоставляться в натуральном виде.Таким образом, ЕДВ составит: 5 830,70 (установленный размер) — 1 331,30 (стоимость социальной услуги по лекарственному обеспечению) = 4 499,40 руб. Санаторно-курортное лечениеВ рамках НСУ людям с инвалидностью выдают бесплатные путевки в санаторий при наличии медицинских показаний. Это право должно быть предусмотрено в индивидуальной программе реабилитации или абилитации (ИПРА), которую оформляют\r\n\t\t\t\t\tпо итогам медико-социальной экспертизы.Длительность лечения в санатории — 18 дней, для детей-инвалидов — 21 день, а для инвалидов с заболеваниями и последствиями травм спинного и головного мозга — от 24 до 42 дней.Инвалиды 1 группы и дети-инвалиды имеют право на получение второй путевки на санаторно-курортное лечение и бесплатный проезд для сопровождающего их лица. Подробно о том, как оформить путевку, читайтев разделе\r\n\t\t\t\t\t«Санаторно-курортное лечение».Проезд к месту лечения и обратноБесплатно добраться до места лечения и обратно можно следующими видами транспорта:железнодорожным (поезда и вагоны всех категорий, за исключением спальных вагонов с двухместными купе и вагонов повышенной комфортности);авиационным (экономический класс);водным (третьей категории);автомобильным (общего пользования).Чтобы оформить бесплатный проезд к месту лечения и обратно, необходимо:Шаг1получить специальный талон на право бесплатного получения проездных документов в поезде дальнего следования или именное направление на приобретение проездных документов на авиационном, автомобильном и водном\r\n\t\t\t\t\t\t\tтранспорте;Шаг2обратиться с талоном или именным направлением в кассу;Шаг3получить бесплатный билет.Талон или именное направление выдадут в отделении СФР при оформлении путевки на санаторно-курортное лечение. Если до места лечения и обратно потребуется воспользоваться двумя и более видами транспорта, выдадут несколько\r\n\t\t\t\t\tспециальных талонов или именных направлений на каждый вид транспорта.Компенсация расходов за самостоятельно приобретенные билеты действующим законодательством не предусмотрена.Бесплатные лекарстваВ рамках НСУ людям с инвалидностью предоставляются:лекарственные препараты из числажизненно необходимых и важнейших;необходимые изделия медицинского назначения;специализированные продукты лечебного питания для детей-инвалидов.Для получения бесплатных лекарств, медицинских изделий или специализированных продуктов питания нужен соответствующий рецепт от врача. Получить его можно в поликлинике по месту жительства или прикрепления.В регистратуре нужно предъявить:паспорт;документ, подтверждающий право на получение НСУ (например, справку, подтверждающую факт установления инвалидности);справку, подтверждающую право на получение НСУ.После проведения осмотра врач назначит необходимые лекарства и выпишет рецепт. С этим рецептом нужно обратиться в льготную аптеку. Адрес ближайшей аптеки можно уточнить при получении рецепта у лечащего врача илина сайте Комитета по здравоохранению.Информацию о наличии льготных лекарств и медицинских изделий в отделах льготного отпуска аптек можно узнать по телефону Справочной службы «Здоровье города» —8 (812) 246-11-11или онлайнна портале. Чтобы отказаться от полного набора или части социальных услуг в натуральной форме и получать вместо этого деньги, нужно подать заявление. Это нужно сделатьдо 1 октябрятекущего года. Тогда с 1 января\r\n\t\t\t\t\tследующего года вместо НСУ будет начисляться его денежный эквивалент.Подать заявление можно онлайнна федеральном портале gosuslugi.ru, в МФЦ или в отделении СФР.Заявление будет действовать до тех пор, пока получатель услуги не передумает и не решит вернуться к натуральной форме набора социальных услуг. Справка о праве на получение НСУ может пригодиться при получении услуг из НСУ в натуральном виде. Выдает такую справку Социальный фонд России. В документе указывается категория льготника, срок установления ежемесячной\r\n\t\t\t\t\tденежной выплаты и набор социальных услуг, на которые инвалид имеет право в текущем году. Справка действует на всей территории России.Заказать ее можно следующими способами:онлайнна федеральном портале gosuslugi.ru;онлайнчерез личный кабинет на сайте СФР;лично в отделении СФР;лично в МФЦ. Социальные выплаты зачисляются только на карту «Мир», на счёт, к которому не привязана ни одна банковская карта, или почтовым переводом.Пенсионеры получают ЕДВ одновременно с пенсией. Для этого нужно обратиться с заявлением в отделение Социального фонда России. Подать заявление можноонлайн. Получить эту информацию можно:онлайнчерез личный кабинет на сайте СФР;лично, обратившись в отделение СФР;лично в МФЦ. Нет. Если вы уже подали заявление об отказе от НСУ в натуральной форме и выбрали денежный эквивалент, ваше заявление будет действовать до тех пор, пока вы не передумаете и не подадите новое заявление. Чтобы со следующего года вместо доплаты к ЕДВ получать социальные услуги в натуральной форме, нужно до 1 октября текущего года подать заявление о возобновлении предоставления набора социальных услугна федеральном портале gosuslugi.ru, в МФЦ или в отделении СФР. Если препарата нет в наличии в аптеке, возможно «отсроченное обслуживание». Ваш рецепт зарегистрируют, и вы сможете получить лекарство позже, когда оно появится. Вам также могут предложить замену препарата на аналог выписанного лекарства.Если вам отказали в выписке рецепта или выдаче бесплатного лекарства, вы вправе обратитьсяв Комитет по здравоохранениюилив Федеральную службу по надзору в сфере здравоохранения. Более подробную информацию о единовременной денежной выплате и наборе социальных услуг можно получить, обратившисьв отделение Социального фонда Россииили в единый контакт центр СФР по телефону8-800-100-00-01."
  },
  {
    "title": "Сертификат молодожёнов",
    "link": "https://gu.spb.ru/knowledge-base/sertifikat-molodozhyenov/",
    "content": "Сертификат молодожёновВ Санкт-Петербурге молодым супругам предоставляется специальный сертификат, по которому можно бесплатно пройти медицинские обследования, чтобы оценить репродуктивную функцию и заранее позаботиться о здоровье будущих детей. С 1 августа 2019 года в Санкт-Петербурге действует программа, по которой супруги, недавно вступившие в брак, могут получить сертификат на бесплатное обследование и консультацию специалиста для оценки репродуктивного здоровья. Сертификат действителен в течение года со дня регистрации брака.Обследование проводится в петербургском«Центре планирования семьи и репродукции»(ЦПСиР). Программа финансируется за счёт средств бюджета Санкт-Петербурга. Чтобы оформить сертификат, нужно обратиться в регистратуру ЦПСиР. Потребуется копия свидетельства о браке и паспорт гражданина РФ. У обоих супругов также должна быть постоянная или временная регистрация в Санкт-Петербурге. Обследование включает консультацию генетика для определения проспективного прогноза потомства, акушера-гинеколога для женщин и уролога-андролога для мужчин, а также ряд медицинских исследований и анализов.Для женщинКонсультация генетикаКонсультация акушера-гинекологаУЗИ малого тазаАнализ на группу крови и резус-факторПЦР диагностика на хламидии, микоплазмы, трихомонады, гонококк, ВПЧ онкогенных подтипов (с 25 лет)Исследование крови на RW, Ф-50, HbSAg, HCVAbМикроскопическое исследование влагалищных мазковОнкоцитологическое исследование мазка из цервикального каналаАнализ крови на антитела к вирусу краснухиДля мужчинКонсультация генетикаКонсультация уролога-андрологаСпермограммаМикроскопическое исследование урогенитального мазкаПЦР диагностика на хламидии, микоплазмы, уреоплазмы, трихомонады, гонококк, вирус простого герпеса 1 и 2 типаИсследование крови на RW, Ф-50, HbSAg, HCVAb Для женщинКонсультация генетикаКонсультация акушера-гинекологаУЗИ малого тазаАнализ на группу крови и резус-факторПЦР диагностика на хламидии, микоплазмы, трихомонады, гонококк, ВПЧ онкогенных подтипов (с 25 лет)Исследование крови на RW, Ф-50, HbSAg, HCVAbМикроскопическое исследование влагалищных мазковОнкоцитологическое исследование мазка из цервикального каналаАнализ крови на антитела к вирусу краснухи Для мужчинКонсультация генетикаКонсультация уролога-андрологаСпермограммаМикроскопическое исследование урогенитального мазкаПЦР диагностика на хламидии, микоплазмы, уреоплазмы, трихомонады, гонококк, вирус простого герпеса 1 и 2 типаИсследование крови на RW, Ф-50, HbSAg, HCVAb Получить интересующую информацию о сертификате молодожёнов и записаться на приём в ЦПСиР можно по телефону8 (812) 670-76-76ина сайте центра."
  }
]